{
  "seed": {
    "secondsUntilRestock": 233,
    "lastRestockAt": 1772407568151,
    "items": [
      {
        "name": "Carrot",
        "stock": 10
      },
      {
        "name": "Cabbage",
        "stock": 2
      },
      {
        "name": "Strawberry",
        "stock": 3
      },
      {
        "name": "Aloe",
        "stock": 9
      },
      {
        "name": "Beet",
        "stock": 6
      },
      {
        "name": "FavaBean",
        "stock": 4
      },
      {
        "name": "Blueberry",
        "stock": 3
      },
      {
        "name": "Watermelon",
        "stock": 3
      },
      {
        "name": "Echeveria",
        "stock": 1
      },
      {
        "name": "Camellia",
        "stock": 1
      },
      {
        "name": "BurrosTail",
        "stock": 2
      }
    ]
  },
  "egg": {
    "secondsUntilRestock": 233,
    "lastRestockAt": 1772407568151,
    "items": [
      {
        "name": "CommonEgg",
        "stock": 2
      },
      {
        "name": "UncommonEgg",
        "stock": 1
      }
    ]
  },
  "decor": {
    "secondsUntilRestock": 2033,
    "lastRestockAt": 1772406663108,
    "items": [
      {
        "name": "SmallRock",
        "stock": 3
      },
      {
        "name": "MediumRock",
        "stock": 3
      },
      {
        "name": "WoodBench",
        "stock": 2
      },
      {
        "name": "WoodArch",
        "stock": 2
      },
      {
        "name": "WoodOwl",
        "stock": 1
      },
      {
        "name": "StoneBench",
        "stock": 2
      },
      {
        "name": "StoneArch",
        "stock": 2
      },
      {
        "name": "MarbleArch",
        "stock": 1
      },
      {
        "name": "MarbleBridge",
        "stock": 1
      },
      {
        "name": "FeedingTrough",
        "stock": 1
      },
      {
        "name": "DecorShed",
        "stock": 1
      },
      {
        "name": "PetHutch",
        "stock": 1
      },
      {
        "name": "SeedSilo",
        "stock": 1
      }
    ]
  }
}
