{
  "seed": {
    "secondsUntilRestock": 178,
    "lastRestockAt": 1772916723222,
    "items": [
      {
        "name": "Carrot",
        "stock": 18
      },
      {
        "name": "Cabbage",
        "stock": 3
      },
      {
        "name": "Strawberry",
        "stock": 4
      },
      {
        "name": "Aloe",
        "stock": 4
      },
      {
        "name": "Beet",
        "stock": 9
      },
      {
        "name": "FavaBean",
        "stock": 5
      },
      {
        "name": "Apple",
        "stock": 1
      },
      {
        "name": "OrangeTulip",
        "stock": 21
      },
      {
        "name": "Pear",
        "stock": 2
      },
      {
        "name": "Camellia",
        "stock": 1
      },
      {
        "name": "Peach",
        "stock": 1
      }
    ]
  },
  "egg": {
    "secondsUntilRestock": 478,
    "lastRestockAt": 1772916723222,
    "items": [
      {
        "name": "CommonEgg",
        "stock": 1
      },
      {
        "name": "UncommonEgg",
        "stock": 1
      }
    ]
  },
  "decor": {
    "secondsUntilRestock": 478,
    "lastRestockAt": 1772914227758,
    "items": [
      {
        "name": "SmallRock",
        "stock": 3
      },
      {
        "name": "MediumRock",
        "stock": 2
      },
      {
        "name": "HayBale",
        "stock": 1
      },
      {
        "name": "WoodBench",
        "stock": 2
      },
      {
        "name": "WoodArch",
        "stock": 2
      },
      {
        "name": "WoodPergola",
        "stock": 2
      },
      {
        "name": "WoodBridge",
        "stock": 2
      },
      {
        "name": "StoneBench",
        "stock": 2
      },
      {
        "name": "StoneArch",
        "stock": 2
      },
      {
        "name": "MarbleArch",
        "stock": 1
      },
      {
        "name": "FeedingTrough",
        "stock": 1
      },
      {
        "name": "DecorShed",
        "stock": 1
      },
      {
        "name": "PetHutch",
        "stock": 1
      },
      {
        "name": "SeedSilo",
        "stock": 1
      }
    ]
  }
}
