{
  "seed": {
    "secondsUntilRestock": 51,
    "lastRestockAt": 1770244450043,
    "items": [
      {
        "name": "Carrot",
        "stock": 15
      },
      {
        "name": "Cabbage",
        "stock": 2
      },
      {
        "name": "Strawberry",
        "stock": 6
      },
      {
        "name": "Aloe",
        "stock": 4
      },
      {
        "name": "Beet",
        "stock": 10
      },
      {
        "name": "Tomato",
        "stock": 2
      },
      {
        "name": "Coconut",
        "stock": 1
      },
      {
        "name": "Lily",
        "stock": 2
      }
    ]
  },
  "egg": {
    "secondsUntilRestock": 651,
    "lastRestockAt": 1770244450043,
    "items": [
      {
        "name": "CommonEgg",
        "stock": 3
      }
    ]
  },
  "decor": {
    "secondsUntilRestock": 1551,
    "lastRestockAt": 1770244450043,
    "items": [
      {
        "name": "SmallRock",
        "stock": 3
      },
      {
        "name": "MediumRock",
        "stock": 2
      },
      {
        "name": "StringLights",
        "stock": 2
      },
      {
        "name": "WoodBench",
        "stock": 2
      },
      {
        "name": "WoodArch",
        "stock": 2
      },
      {
        "name": "WoodPergola",
        "stock": 2
      },
      {
        "name": "StoneBench",
        "stock": 2
      },
      {
        "name": "StoneArch",
        "stock": 2
      },
      {
        "name": "StoneBridge",
        "stock": 2
      },
      {
        "name": "MarbleBench",
        "stock": 1
      },
      {
        "name": "PetHutch",
        "stock": 1
      },
      {
        "name": "DecorShed",
        "stock": 1
      },
      {
        "name": "SeedSilo",
        "stock": 1
      }
    ]
  }
}
