{
  "seed": {
    "secondsUntilRestock": 142,
    "lastRestockAt": 1770576760016,
    "items": [
      {
        "name": "Carrot",
        "stock": 8
      },
      {
        "name": "Cabbage",
        "stock": 3
      },
      {
        "name": "Strawberry",
        "stock": 4
      },
      {
        "name": "Aloe",
        "stock": 5
      },
      {
        "name": "Beet",
        "stock": 9
      },
      {
        "name": "FavaBean",
        "stock": 2
      },
      {
        "name": "Apple",
        "stock": 1
      },
      {
        "name": "Tomato",
        "stock": 1
      },
      {
        "name": "Daffodil",
        "stock": 3
      },
      {
        "name": "Pear",
        "stock": 2
      },
      {
        "name": "Lily",
        "stock": 1
      }
    ]
  },
  "egg": {
    "secondsUntilRestock": 442,
    "lastRestockAt": 1770576760016,
    "items": [
      {
        "name": "CommonEgg",
        "stock": 1
      },
      {
        "name": "UncommonEgg",
        "stock": 1
      }
    ]
  },
  "decor": {
    "secondsUntilRestock": 442,
    "lastRestockAt": 1770573673201,
    "items": [
      {
        "name": "SmallRock",
        "stock": 3
      },
      {
        "name": "MediumRock",
        "stock": 2
      },
      {
        "name": "HayBale",
        "stock": 1
      },
      {
        "name": "StringLights",
        "stock": 2
      },
      {
        "name": "WoodBench",
        "stock": 2
      },
      {
        "name": "WoodArch",
        "stock": 2
      },
      {
        "name": "StoneBench",
        "stock": 2
      },
      {
        "name": "StoneArch",
        "stock": 2
      },
      {
        "name": "MarbleBench",
        "stock": 1
      },
      {
        "name": "MarbleArch",
        "stock": 1
      },
      {
        "name": "PetHutch",
        "stock": 1
      },
      {
        "name": "DecorShed",
        "stock": 1
      },
      {
        "name": "SeedSilo",
        "stock": 1
      }
    ]
  }
}
